reinforcenow/__init__.py
reinforcenow-10.0.1.dist-info/METADATA
reinforcenow-10.0.1.dist-info/WHEEL
reinforcenow-10.0.1.dist-info/entry_points.txt
reinforcenow-10.0.1.dist-info/top_level.txt
reinforcenow-10.0.1.dist-info/RECORD
