Metadata-Version: 2.4
Name: reinforcenow
Version: 10.0.1
Summary: This package has been renamed to 'rnow'. Please install 'rnow' instead.
Classifier: Development Status :: 7 - Inactive
Classifier: Programming Language :: Python :: 3
Classifier: License :: OSI Approved :: MIT License
Requires-Python: >=3.7
